righor-0.2.97.data/data/righor_models/human/b_heavy/J_gene_CDR3_anchors.csv
righor-0.2.97.data/data/righor_models/human/b_heavy/V_gene_CDR3_anchors.csv
righor-0.2.97.data/data/righor_models/human/b_heavy/tmp1/model_marginals.txt
righor-0.2.97.data/data/righor_models/human/b_heavy/tmp1/model_params.txt
righor-0.2.97.data/data/righor_models/human/b_kappa/J_gene_CDR3_anchors.csv
righor-0.2.97.data/data/righor_models/human/b_kappa/V_gene_CDR3_anchors.csv
righor-0.2.97.data/data/righor_models/human/b_kappa/tmp1/model_marginals.txt
righor-0.2.97.data/data/righor_models/human/b_kappa/tmp1/model_params.txt
righor-0.2.97.data/data/righor_models/human/b_kappa/tmp1/model_parms.txt
righor-0.2.97.data/data/righor_models/human/b_lambda/J_gene_CDR3_anchors.csv
righor-0.2.97.data/data/righor_models/human/b_lambda/V_gene_CDR3_anchors.csv
righor-0.2.97.data/data/righor_models/human/b_lambda/tmp1/model_marginals.txt
righor-0.2.97.data/data/righor_models/human/b_lambda/tmp1/model_params.txt
righor-0.2.97.data/data/righor_models/human/b_lambda/tmp1/model_parms.txt
righor-0.2.97.data/data/righor_models/human/t_alpha/J_gene_CDR3_anchors.csv
righor-0.2.97.data/data/righor_models/human/t_alpha/V_gene_CDR3_anchors.csv
righor-0.2.97.data/data/righor_models/human/t_alpha/model_marginals.txt
righor-0.2.97.data/data/righor_models/human/t_alpha/model_params.txt
righor-0.2.97.data/data/righor_models/human/t_alpha/tmp1/model_marginals.txt
righor-0.2.97.data/data/righor_models/human/t_alpha/tmp1/model_params.txt
righor-0.2.97.data/data/righor_models/human/t_beta/J_gene_CDR3_anchors.csv
righor-0.2.97.data/data/righor_models/human/t_beta/V_gene_CDR3_anchors.csv
righor-0.2.97.data/data/righor_models/human/t_beta/tmp1/model_marginals.txt
righor-0.2.97.data/data/righor_models/human/t_beta/tmp1/model_params.txt
righor-0.2.97.data/data/righor_models/models.json
righor-0.2.97.data/data/righor_models/mouse/t_alpha/J_gene_CDR3_anchors.csv
righor-0.2.97.dist-info/METADATA
righor-0.2.97.dist-info/WHEEL
righor-0.2.97.dist-info/RECORD
