Metadata-Version: 2.4
Name: righor
Version: 0.2.97
Requires-Dist: seaborn
Requires-Dist: matplotlib
Requires-Dist: tqdm
Requires-Dist: numpy
Summary: Righor creates model of Ig/TCR sequences from sequencing data.
License: MIT
Project-URL: Source Code, https://github.com/Thopic/righor
